streaming_infer/__init__.py
streaming_infer/local_test.py
streaming_infer/main.py
streaming_infer/supervisor.py
streaming_infer/worker.py
streaming_infer/config/__init__.py
streaming_infer/config/job_config.py
streaming_infer/pipeline/__init__.py
streaming_infer/pipeline/factory.py
streaming_infer/pipeline/infer_handler.py
streaming_infer/pipeline/infer_report.py
streaming_infer/pipeline/pipeline.py
streaming_infer/products/__init__.py
streaming_infer/products/example/__init__.py
streaming_infer/products/example/pipeline.py
streaming_infer/products/example/task.py
streaming_infer/products/example/task_manager.py
streaming_infer/products/soe/__init__.py
streaming_infer/products/soe/pipeline.py
streaming_infer/products/soe/soe_point.py
streaming_infer/products/soe/task.py
streaming_infer/products/soe/task_manager.py
streaming_infer/streamz_ext/__init__.py
streaming_infer/streamz_ext/core.py
streaming_infer/streamz_ext/sqlalchemy_connection.py
streaming_infer/streamz_ext/sinks/__init__.py
streaming_infer/streamz_ext/sinks/http.py
streaming_infer/streamz_ext/sinks/mysql.py
streaming_infer/streamz_ext/sources/__init__.py
streaming_infer/streamz_ext/sources/jetstream.py
streaming_infer/tasks/__init__.py
streaming_infer/tasks/sink_config.py
streaming_infer/tasks/source_config.py
streaming_infer/tasks/task_config.py
streaming_infer/tasks/task_manager.py
streaming_infer/test/__init__.py
streaming_infer/test/config/__init__.py
streaming_infer/test/config/test_job_config.py
streaming_infer/test/products/__init__.py
streaming_infer/test/products/soe/__init__.py
streaming_infer/test/products/soe/test_soe_pipline.py
streaming_infer/test/streamz_ext/__init__.py
streaming_infer/test/streamz_ext/test_streamz.py
streaming_infer-0.1.1.dist-info/METADATA
streaming_infer-0.1.1.dist-info/WHEEL
streaming_infer-0.1.1.dist-info/top_level.txt
streaming_infer-0.1.1.dist-info/RECORD
