Metadata-Version: 2.1
Name: streaming-infer
Version: 0.1.1
Summary: streaming_infer
Home-page: http://icode.baidu.com/repos/baidu/themis/lakeinsight-analytics-ray/tree/master/streaming-infer
Author: acg-soe
Author-email: zhoubohan.pro@gmail.com
License: LICENSE.txt
Platform: UNKNOWN
Classifier: Programming Language :: Python
Classifier: Programming Language :: Python :: 3
Classifier: Programming Language :: Python :: 3.7
Classifier: Programming Language :: Python :: 3.8
Classifier: Programming Language :: Python :: 3.9
Requires-Python: >=3.9
Requires-Dist: boto3 (==1.26.130)
Requires-Dist: numpy (==1.24.3)
Requires-Dist: paho-mqtt (==1.6.1)
Requires-Dist: pandas (==2.0.1)
Requires-Dist: PyYAML (==6.0)
Requires-Dist: ray (==2.6.1)
Requires-Dist: Requests (==2.30.0)
Requires-Dist: setuptools (==58.0.4)
Requires-Dist: torch (==2.0.1)
Requires-Dist: torchlibrosa (==0.1.0)
Requires-Dist: tornado (==6.3.2)
Requires-Dist: tritonclient (==2.34.0)
Requires-Dist: tritonv2 (==0.9.6)
Requires-Dist: sqlalchemy-utils (==0.41.1)
Requires-Dist: sqlalchemy (==1.4.47)
Requires-Dist: streamz (==0.6.3)
Requires-Dist: nats-py (==2.2.0)
Requires-Dist: arrow (==1.2.3)
Requires-Dist: pydantic (==1.10.12)
Requires-Dist: pymysql (==1.1.0)
